agentp/GREX.py
agentp/GWAS.py
agentp/Genotypes.py
agentp/Project.py
agentp/Static.py
agentp/TWAS.py
agentp/__init__.py
agentp/external/MetaXcan/M03_betas.py
agentp/external/MetaXcan/M04_zscores.py
agentp/external/MetaXcan/PrediXcanAssociation.py
agentp/external/MetaXcan/Predict.py
agentp/external/MetaXcan/SPrediXcan.py
agentp/external/MetaXcan/metax/Constants.py
agentp/external/MetaXcan/metax/Exceptions.py
agentp/external/MetaXcan/metax/Logging.py
agentp/external/MetaXcan/metax/MatrixManager.py
agentp/external/MetaXcan/metax/NamingConventions.py
agentp/external/MetaXcan/metax/PredictionModel.py
agentp/external/MetaXcan/metax/Utilities.py
agentp/external/MetaXcan/metax/__init__.py
agentp/external/MetaXcan/metax/expression/Expression.py
agentp/external/MetaXcan/metax/expression/HDF5Expression.py
agentp/external/MetaXcan/metax/expression/PlainTextExpression.py
agentp/external/MetaXcan/metax/genotype/DosageGenotype.py
agentp/external/MetaXcan/metax/genotype/Genotype.py
agentp/external/MetaXcan/metax/gwas/GWAS.py
agentp/external/MetaXcan/metax/gwas/GWASSpecialHandling.py
agentp/external/MetaXcan/metax/gwas/Utilities.py
agentp/external/MetaXcan/metax/metaxcan/AssociationCalculation.py
agentp/external/MetaXcan/metax/metaxcan/Utilities.py
agentp/external/MetaXcan/metax/misc/DataFrameStreamer.py
agentp/external/MetaXcan/metax/misc/GWASAndModels.py
agentp/external/MetaXcan/metax/misc/Genomics.py
agentp/external/MetaXcan/metax/misc/KeyedDataSource.py
agentp/external/MetaXcan/metax/misc/Math.py
agentp/external/MetaXcan/metax/predixcan/MultiPrediXcanAssociation.py
agentp/external/MetaXcan/metax/predixcan/PrediXcanAssociation.py
agentp/external/MetaXcan/metax/predixcan/Utilities.py
agentp/external/fusion_twas/FUSION.assoc_test.R
agentp/external/fusion_twas/FUSION.compute_weights.R
agentp/external/fusion_twas/FUSION.post_process.R
agentp/external/fusion_twas/LICENSE
agentp/external/fusion_twas/README.md
agentp/external/fusion_twas/gcta_nr_robust
agentp-0.1.0.dist-info/METADATA
agentp-0.1.0.dist-info/WHEEL
agentp-0.1.0.dist-info/top_level.txt
agentp-0.1.0.dist-info/RECORD
