Metadata-Version: 2.1
Name: agentp
Version: 0.1.0
Summary: Associating Gene Expression to Neuroimaging Traits Pipeline (AGENT-P)
Home-page: https://github.com/nhunghoang/neurogen
Author: Nhung Hoang
Author-email: nhung.hoang@vanderbilt.edu
License: MIT
Classifier: Programming Language :: Python :: 3
Requires-Python: >=3.8
Requires-Dist: bgen_reader
Requires-Dist: h5py
Requires-Dist: numpy
Requires-Dist: pandas
Requires-Dist: patsy
Requires-Dist: bitarray
Requires-Dist: scipy
Requires-Dist: statsmodels
Requires-Dist: pyliftover
Requires-Dist: setuptools
